tidelog/__init__.py
tidelog/_types.py
tidelog/context.py
tidelog/interfaces.py
tidelog/log_record.py
tidelog/models.py
tidelog/py.typed
tidelog/utils.py
tidelog-0.0.3.dist-info/METADATA
tidelog-0.0.3.dist-info/WHEEL
tidelog-0.0.3.dist-info/RECORD
