Metadata-Version: 2.4
Name: tidelog
Version: 0.0.3
Summary: Add your description here
Author-email: nafnix <uwu@nafnix.com>
Requires-Python: >=3.11
Requires-Dist: fastapi>=0.28.0
